envmate/__init__.py
envmate/main.py
envmate-0.5.0.dist-info/LICENSE
envmate-0.5.0.dist-info/METADATA
envmate-0.5.0.dist-info/WHEEL
envmate-0.5.0.dist-info/entry_points.txt
envmate-0.5.0.dist-info/top_level.txt
envmate-0.5.0.dist-info/RECORD
