Metadata-Version: 2.1
Name: envmate
Version: 0.5.0
Summary: A tool to configure environment variables interactively.
Home-page: https://github.com/harris-ahmad/envmate
Author: Harris Ahmad
Author-email: harris.ahmad55@gmail.com
Classifier: Programming Language :: Python :: 3
Classifier: License :: OSI Approved :: MIT License
Classifier: Operating System :: OS Independent
Requires-Python: >=3.6
License-File: LICENSE
Requires-Dist: inquirer
